[
    {
        "client": 10,
        "strategy": "fedmedian",
        "type": "data",
        "attackers": 0.0,
        "loss_fit": [
            [
                1,
                1.6027644201662448
            ],
            [
                2,
                0.8351943596521219
            ],
            [
                3,
                0.6586276867294302
            ],
            [
                4,
                0.5849352939474867
            ],
            [
                5,
                0.5417269889545113
            ],
            [
                6,
                0.5127102480989846
            ],
            [
                7,
                0.49136672918343755
            ],
            [
                8,
                0.4745777641352122
            ],
            [
                9,
                0.46076811237693616
            ],
            [
                10,
                0.44908660202354306
            ],
            [
                11,
                0.4392989461902144
            ],
            [
                12,
                0.4302021581612184
            ],
            [
                13,
                0.4221403331325158
            ],
            [
                14,
                0.41453732544586736
            ],
            [
                15,
                0.40874889486334115
            ],
            [
                16,
                0.4023086211720858
            ],
            [
                17,
                0.39696781451080676
            ],
            [
                18,
                0.39201219664616155
            ],
            [
                19,
                0.3865343582750414
            ],
            [
                20,
                0.3815129313049132
            ],
            [
                21,
                0.37738805124371544
            ],
            [
                22,
                0.373576618709444
            ],
            [
                23,
                0.3696444404467976
            ],
            [
                24,
                0.3657574799845946
            ],
            [
                25,
                0.3619373275307884
            ],
            [
                26,
                0.3586339790945829
            ],
            [
                27,
                0.3552886607637876
            ],
            [
                28,
                0.351474155190163
            ],
            [
                29,
                0.3481654750813162
            ],
            [
                30,
                0.34539880147585755
            ],
            [
                31,
                0.34233702846929903
            ],
            [
                32,
                0.33926590114793637
            ],
            [
                33,
                0.33639451993767305
            ],
            [
                34,
                0.3335977254924221
            ],
            [
                35,
                0.33080226152519016
            ],
            [
                36,
                0.32810175569252154
            ],
            [
                37,
                0.3256971626887037
            ],
            [
                38,
                0.323298304691281
            ],
            [
                39,
                0.32061491959850263
            ],
            [
                40,
                0.31864433378286744
            ],
            [
                41,
                0.31551571549502255
            ],
            [
                42,
                0.3135660956272231
            ],
            [
                43,
                0.31146689461146426
            ],
            [
                44,
                0.3089869202325344
            ],
            [
                45,
                0.3062743181842365
            ],
            [
                46,
                0.304618366508015
            ],
            [
                47,
                0.30225959601520513
            ],
            [
                48,
                0.3002113598277812
            ],
            [
                49,
                0.2982377593678664
            ],
            [
                50,
                0.2963326132394901
            ]
        ],
        "accuracy_fit": [
            [
                1,
                0.49421814772372114
            ],
            [
                2,
                0.7214501510574018
            ],
            [
                3,
                0.7649616279473557
            ],
            [
                4,
                0.788797444178213
            ],
            [
                5,
                0.8055005729763517
            ],
            [
                6,
                0.8154113275688439
            ],
            [
                7,
                0.8245372781887003
            ],
            [
                8,
                0.8306212452686044
            ],
            [
                9,
                0.8359481890474703
            ],
            [
                10,
                0.8395596763551758
            ],
            [
                11,
                0.8429766989616975
            ],
            [
                12,
                0.8465812411015036
            ],
            [
                13,
                0.8497274021599474
            ],
            [
                14,
                0.8522484981074419
            ],
            [
                15,
                0.8542625967982775
            ],
            [
                16,
                0.8558391499114492
            ],
            [
                17,
                0.8574920998715143
            ],
            [
                18,
                0.8591103239920825
            ],
            [
                19,
                0.8621870333715317
            ],
            [
                20,
                0.8636038476230162
            ],
            [
                21,
                0.8650970587213945
            ],
            [
                22,
                0.867006979893739
            ],
            [
                23,
                0.8677709483626768
            ],
            [
                24,
                0.8691460916067647
            ],
            [
                25,
                0.8709032190853212
            ],
            [
                26,
                0.8721533493072193
            ],
            [
                27,
                0.8729589887835538
            ],
            [
                28,
                0.8748758551237976
            ],
            [
                29,
                0.8758967948050144
            ],
            [
                30,
                0.8765010244122651
            ],
            [
                31,
                0.8777719901378617
            ],
            [
                32,
                0.8793693787547313
            ],
            [
                33,
                0.8798624856755912
            ],
            [
                34,
                0.8811195610653888
            ],
            [
                35,
                0.8821960620898008
            ],
            [
                36,
                0.8828766885439459
            ],
            [
                37,
                0.8837865055387712
            ],
            [
                38,
                0.8841893252769387
            ],
            [
                39,
                0.8856547557037191
            ],
            [
                40,
                0.8861756432961767
            ],
            [
                41,
                0.8875785672118623
            ],
            [
                42,
                0.8885925617251799
            ],
            [
                43,
                0.8891065041497378
            ],
            [
                44,
                0.8895093238879052
            ],
            [
                45,
                0.8908566864603952
            ],
            [
                46,
                0.8912942320380596
            ],
            [
                47,
                0.8920165294996005
            ],
            [
                48,
                0.8935305761016774
            ],
            [
                49,
                0.8940653540299336
            ],
            [
                50,
                0.8942181477237213
            ]
        ],
        "loss_eval": [
            [
                1,
                1.0447305753398866
            ],
            [
                2,
                0.7226934687786428
            ],
            [
                3,
                0.6194597826307885
            ],
            [
                4,
                0.5654884380432329
            ],
            [
                5,
                0.5309605146189225
            ],
            [
                6,
                0.5070968760941635
            ],
            [
                7,
                0.4888862885072399
            ],
            [
                8,
                0.4744957358402195
            ],
            [
                9,
                0.4620201776197482
            ],
            [
                10,
                0.4518040523410886
            ],
            [
                11,
                0.44277164919929474
            ],
            [
                12,
                0.435331795278662
            ],
            [
                13,
                0.4289716074835107
            ],
            [
                14,
                0.42282835751312664
            ],
            [
                15,
                0.4166416477481806
            ],
            [
                16,
                0.41189433755054417
            ],
            [
                17,
                0.40772660763399743
            ],
            [
                18,
                0.4027623400768604
            ],
            [
                19,
                0.3994435020110747
            ],
            [
                20,
                0.3941205647576605
            ],
            [
                21,
                0.3928863396152066
            ],
            [
                22,
                0.38664074688094796
            ],
            [
                23,
                0.3838506471460335
            ],
            [
                24,
                0.3807677735690522
            ],
            [
                25,
                0.37768929988729216
            ],
            [
                26,
                0.3767688611307426
            ],
            [
                27,
                0.37224278575874575
            ],
            [
                28,
                0.3701972063210347
            ],
            [
                29,
                0.36703512038056524
            ],
            [
                30,
                0.3673733230309405
            ],
            [
                31,
                0.36327843608731086
            ],
            [
                32,
                0.3608348009016354
            ],
            [
                33,
                0.3608049853599752
            ],
            [
                34,
                0.356664292112781
            ],
            [
                35,
                0.3552292294325505
            ],
            [
                36,
                0.3548565847210366
            ],
            [
                37,
                0.35198719321514654
            ],
            [
                38,
                0.3495645174752767
            ],
            [
                39,
                0.3483180322159533
            ],
            [
                40,
                0.34822377729098136
            ],
            [
                41,
                0.3454643501931556
            ],
            [
                42,
                0.3434866043514433
            ],
            [
                43,
                0.34171104361890803
            ],
            [
                44,
                0.3410069236776224
            ],
            [
                45,
                0.3407547687774199
            ],
            [
                46,
                0.3379653090340353
            ],
            [
                47,
                0.3371775247290054
            ],
            [
                48,
                0.33572229823933103
            ],
            [
                49,
                0.3353400087068598
            ],
            [
                50,
                0.3335039842357143
            ]
        ],
        "accuracy_eval": [
            [
                1,
                0.6790503956684715
            ],
            [
                2,
                0.7486047480216577
            ],
            [
                3,
                0.7765097875885048
            ],
            [
                4,
                0.7911703456892961
            ],
            [
                5,
                0.804414827155352
            ],
            [
                6,
                0.8184922948771345
            ],
            [
                7,
                0.8249062890462308
            ],
            [
                8,
                0.831820074968763
            ],
            [
                9,
                0.8366513952519783
            ],
            [
                10,
                0.8413161182840483
            ],
            [
                11,
                0.8452311536859641
            ],
            [
                12,
                0.848646397334444
            ],
            [
                13,
                0.8505622657226156
            ],
            [
                14,
                0.8522282382340691
            ],
            [
                15,
                0.8548937942523949
            ],
            [
                16,
                0.8567263640149938
            ],
            [
                17,
                0.858725531028738
            ],
            [
                18,
                0.8593086214077468
            ],
            [
                19,
                0.8602249062890462
            ],
            [
                20,
                0.8607246980424823
            ],
            [
                21,
                0.8618908788004997
            ],
            [
                22,
                0.8627238650562266
            ],
            [
                23,
                0.8633069554352353
            ],
            [
                24,
                0.8649729279466889
            ],
            [
                25,
                0.8661391087047063
            ],
            [
                26,
                0.8657226155768429
            ],
            [
                27,
                0.8682215743440234
            ],
            [
                28,
                0.8687213660974594
            ],
            [
                29,
                0.8690545605997501
            ],
            [
                30,
                0.86780508121616
            ],
            [
                31,
                0.8711370262390671
            ],
            [
                32,
                0.8716368179925031
            ],
            [
                33,
                0.8704706372344856
            ],
            [
                34,
                0.8723865056226572
            ],
            [
                35,
                0.8733860891295293
            ],
            [
                36,
                0.8726364014993753
            ],
            [
                37,
                0.8743856726364015
            ],
            [
                38,
                0.8736359850062474
            ],
            [
                39,
                0.8748854643898376
            ],
            [
                40,
                0.8747188671386922
            ],
            [
                41,
                0.876051645147855
            ],
            [
                42,
                0.8764681382757185
            ],
            [
                43,
                0.8782174094127447
            ],
            [
                44,
                0.8766347355268638
            ],
            [
                45,
                0.8788837984173261
            ],
            [
                46,
                0.878134110787172
            ],
            [
                47,
                0.8775510204081632
            ],
            [
                48,
                0.8793835901707622
            ],
            [
                49,
                0.8776343190337359
            ],
            [
                50,
                0.8785506039150354
            ]
        ]
    },
    {
        "client": 10,
        "strategy": "fedmedian",
        "type": "data",
        "attackers": 0.25,
        "loss_fit": [
            [
                1,
                1.5587382055845687
            ],
            [
                2,
                0.8134711927430731
            ],
            [
                3,
                0.7355523650520448
            ],
            [
                4,
                0.5781332701766483
            ],
            [
                5,
                0.6466744328348671
            ],
            [
                6,
                0.5057800050627859
            ],
            [
                7,
                0.6068269801716484
            ],
            [
                8,
                0.46789421888177185
            ],
            [
                9,
                0.5824885899260477
            ],
            [
                10,
                0.4436248438545295
            ],
            [
                11,
                0.5659535228656548
            ],
            [
                12,
                0.42665385198737205
            ],
            [
                13,
                0.5505026250455671
            ],
            [
                14,
                0.4121477063045273
            ],
            [
                15,
                0.5393516878837569
            ],
            [
                16,
                0.39986795052727153
            ],
            [
                17,
                0.5267103962731924
            ],
            [
                18,
                0.38930608434106195
            ],
            [
                19,
                0.5172211237511263
            ],
            [
                20,
                0.3797242543986263
            ],
            [
                21,
                0.5065186209028436
            ],
            [
                22,
                0.37097384927587157
            ],
            [
                23,
                0.496809371896744
            ],
            [
                24,
                0.36322020173940067
            ],
            [
                25,
                0.4886870214026544
            ],
            [
                26,
                0.35556548355164636
            ],
            [
                27,
                0.4786017892908941
            ],
            [
                28,
                0.34824928414466855
            ],
            [
                29,
                0.47075364794944996
            ],
            [
                30,
                0.34172907183946455
            ],
            [
                31,
                0.46309222130730837
            ],
            [
                32,
                0.3358125090756366
            ],
            [
                33,
                0.4554656280890347
            ],
            [
                34,
                0.32955266212917816
            ],
            [
                35,
                0.4485663101122616
            ],
            [
                36,
                0.3239746834695325
            ],
            [
                37,
                0.4421629953096488
            ],
            [
                38,
                0.3187920488626459
            ],
            [
                39,
                0.4355843637460333
            ],
            [
                40,
                0.3136217508735551
            ],
            [
                41,
                0.4290631227658644
            ],
            [
                42,
                0.3087483832559788
            ],
            [
                43,
                0.4232163384526241
            ],
            [
                44,
                0.3044950106462538
            ],
            [
                45,
                0.4168891424799402
            ],
            [
                46,
                0.29945768087897434
            ],
            [
                47,
                0.4111408057085784
            ],
            [
                48,
                0.29529606353765925
            ],
            [
                49,
                0.4060666060925407
            ],
            [
                50,
                0.29082845189415973
            ]
        ],
        "accuracy_fit": [
            [
                1,
                0.4975726638191478
            ],
            [
                2,
                0.7309511407438275
            ],
            [
                3,
                0.7237698371358127
            ],
            [
                4,
                0.794270236482967
            ],
            [
                5,
                0.7553495155745389
            ],
            [
                6,
                0.8204257387922353
            ],
            [
                7,
                0.7739972913845192
            ],
            [
                8,
                0.8345174844601869
            ],
            [
                9,
                0.7836302392610341
            ],
            [
                10,
                0.8422335659964582
            ],
            [
                11,
                0.7909990624023335
            ],
            [
                12,
                0.848123068375178
            ],
            [
                13,
                0.7971247004896341
            ],
            [
                14,
                0.854366774316769
            ],
            [
                15,
                0.8021460568809252
            ],
            [
                16,
                0.8585616557280272
            ],
            [
                17,
                0.8071813036080149
            ],
            [
                18,
                0.861791158801264
            ],
            [
                19,
                0.8112164461575859
            ],
            [
                20,
                0.8645553356252388
            ],
            [
                21,
                0.8148418238010903
            ],
            [
                22,
                0.8675556481577941
            ],
            [
                23,
                0.819814564017085
            ],
            [
                24,
                0.8703614959891657
            ],
            [
                25,
                0.8232871479668024
            ],
            [
                26,
                0.8739174219536758
            ],
            [
                27,
                0.827752890926138
            ],
            [
                28,
                0.8765357502517626
            ],
            [
                29,
                0.8301211931798452
            ],
            [
                30,
                0.8795430079522173
            ],
            [
                31,
                0.8327256311421328
            ],
            [
                32,
                0.8810501093863944
            ],
            [
                33,
                0.8372677709483626
            ],
            [
                34,
                0.8834600826474981
            ],
            [
                35,
                0.8398930444143486
            ],
            [
                36,
                0.885203319790256
            ],
            [
                37,
                0.8418238010903915
            ],
            [
                38,
                0.886613188873841
            ],
            [
                39,
                0.8440948709935062
            ],
            [
                40,
                0.8893287495225197
            ],
            [
                41,
                0.8474632774247319
            ],
            [
                42,
                0.8905372087370212
            ],
            [
                43,
                0.8499218668611314
            ],
            [
                44,
                0.8916553807688302
            ],
            [
                45,
                0.8523457304580337
            ],
            [
                46,
                0.8937667118102579
            ],
            [
                47,
                0.8542834323019761
            ],
            [
                48,
                0.895301593916033
            ],
            [
                49,
                0.855644685210265
            ],
            [
                50,
                0.8967184081675175
            ]
        ],
        "loss_eval": [
            [
                1,
                1.232428824509347
            ],
            [
                2,
                0.7231493867918235
            ],
            [
                3,
                1.138569419322437
            ],
            [
                4,
                0.5736522596957832
            ],
            [
                5,
                1.1970150696292912
            ],
            [
                6,
                0.5115818475892473
            ],
            [
                7,
                1.240072062456424
            ],
            [
                8,
                0.47895573018889087
            ],
            [
                9,
                1.2710655023633615
            ],
            [
                10,
                0.4574541213436953
            ],
            [
                11,
                1.2939881430075397
            ],
            [
                12,
                0.4425271785269177
            ],
            [
                13,
                1.3154508104526912
            ],
            [
                14,
                0.43282111442769283
            ],
            [
                15,
                1.3327817281500989
            ],
            [
                16,
                0.4202167166863219
            ],
            [
                17,
                1.3395536741009855
            ],
            [
                18,
                0.4128747225204938
            ],
            [
                19,
                1.3533240621882348
            ],
            [
                20,
                0.405279605011799
            ],
            [
                21,
                1.357376598517431
            ],
            [
                22,
                0.39840784611576846
            ],
            [
                23,
                1.3630236338595956
            ],
            [
                24,
                0.39125062031876984
            ],
            [
                25,
                1.3734016643147426
            ],
            [
                26,
                0.3864027860089175
            ],
            [
                27,
                1.375755478024036
            ],
            [
                28,
                0.38347708967912697
            ],
            [
                29,
                1.3847962584161897
            ],
            [
                30,
                0.37695944919679525
            ],
            [
                31,
                1.3897156416227896
            ],
            [
                32,
                0.3724393477865876
            ],
            [
                33,
                1.3896802363222909
            ],
            [
                34,
                0.36953781205929603
            ],
            [
                35,
                1.3911193504426838
            ],
            [
                36,
                0.36565856799539154
            ],
            [
                37,
                1.396266540397162
            ],
            [
                38,
                0.3624562994930358
            ],
            [
                39,
                1.405435523950572
            ],
            [
                40,
                0.35939764226788734
            ],
            [
                41,
                1.4064257432971583
            ],
            [
                42,
                0.3566500302902215
            ],
            [
                43,
                1.4096376270390907
            ],
            [
                44,
                0.35342063142179897
            ],
            [
                45,
                1.4153901326810256
            ],
            [
                46,
                0.35260673258663067
            ],
            [
                47,
                1.430283788873076
            ],
            [
                48,
                0.3527095879206604
            ],
            [
                49,
                1.4201375567779
            ],
            [
                50,
                0.3484866118242422
            ]
        ],
        "accuracy_eval": [
            [
                1,
                0.5675968346522282
            ],
            [
                2,
                0.751603498542274
            ],
            [
                3,
                0.638817159516868
            ],
            [
                4,
                0.799750104123282
            ],
            [
                5,
                0.661557684298209
            ],
            [
                6,
                0.8221574344023324
            ],
            [
                7,
                0.6718867138692212
            ],
            [
                8,
                0.8330695543523532
            ],
            [
                9,
                0.6789670970428988
            ],
            [
                10,
                0.8408163265306122
            ],
            [
                11,
                0.6834652228238234
            ],
            [
                12,
                0.8468971261974177
            ],
            [
                13,
                0.6867138692211578
            ],
            [
                14,
                0.8471470220741357
            ],
            [
                15,
                0.6877967513536026
            ],
            [
                16,
                0.8529779258642233
            ],
            [
                17,
                0.6918783840066639
            ],
            [
                18,
                0.8558100791336943
            ],
            [
                19,
                0.6902124114952103
            ],
            [
                20,
                0.8581424406497293
            ],
            [
                21,
                0.6908788004997918
            ],
            [
                22,
                0.8611411911703457
            ],
            [
                23,
                0.6946272386505623
            ],
            [
                24,
                0.8633069554352353
            ],
            [
                25,
                0.6959600166597251
            ],
            [
                26,
                0.8656393169512703
            ],
            [
                27,
                0.6973760932944606
            ],
            [
                28,
                0.8643898375676802
            ],
            [
                29,
                0.6974593919200334
            ],
            [
                30,
                0.8669720949604331
            ],
            [
                31,
                0.6957101207830071
            ],
            [
                32,
                0.8681382757184506
            ],
            [
                33,
                0.7015410245730945
            ],
            [
                34,
                0.8705539358600584
            ],
            [
                35,
                0.7013744273219492
            ],
            [
                36,
                0.8718034152436485
            ],
            [
                37,
                0.7033735943356935
            ],
            [
                38,
                0.8721366097459392
            ],
            [
                39,
                0.7042898792169929
            ],
            [
                40,
                0.8733027905039566
            ],
            [
                41,
                0.7052894627238651
            ],
            [
                42,
                0.8747188671386922
            ],
            [
                43,
                0.7055393586005831
            ],
            [
                44,
                0.8750520616409829
            ],
            [
                45,
                0.7045397750937109
            ],
            [
                46,
                0.8753852561432737
            ],
            [
                47,
                0.7018742190753853
            ],
            [
                48,
                0.8744689712619742
            ],
            [
                49,
                0.7072886297376093
            ],
            [
                50,
                0.8757184506455643
            ]
        ]
    },
    {
        "client": 10,
        "strategy": "fedmedian",
        "type": "data",
        "attackers": 0.5,
        "loss_fit": [
            [
                1,
                1.5096793121781062
            ],
            [
                2,
                0.9327860123606885
            ],
            [
                3,
                0.8428804823218997
            ],
            [
                4,
                0.6668860340808073
            ],
            [
                5,
                0.7528068843022666
            ],
            [
                6,
                0.5837221475549053
            ],
            [
                7,
                0.6998625139714147
            ],
            [
                8,
                0.5403774148640369
            ],
            [
                9,
                0.6593895352171971
            ],
            [
                10,
                0.5118374533022709
            ],
            [
                11,
                0.626020462086297
            ],
            [
                12,
                0.48910655794605
            ],
            [
                13,
                0.5987939023725664
            ],
            [
                14,
                0.4704352051452262
            ],
            [
                15,
                0.5760949362422143
            ],
            [
                16,
                0.45619779118345893
            ],
            [
                17,
                0.5568279190778931
            ],
            [
                18,
                0.44282996256623564
            ],
            [
                19,
                0.538624145261185
            ],
            [
                20,
                0.43235314828606786
            ],
            [
                21,
                0.5225289396470002
            ],
            [
                22,
                0.42166414977953853
            ],
            [
                23,
                0.5076768447610824
            ],
            [
                24,
                0.4133384745242169
            ],
            [
                25,
                0.49422952659679337
            ],
            [
                26,
                0.4057248398862645
            ],
            [
                27,
                0.4831464778005934
            ],
            [
                28,
                0.39735292461588667
            ],
            [
                29,
                0.4711800654335941
            ],
            [
                30,
                0.39068632062962977
            ],
            [
                31,
                0.46191429168577886
            ],
            [
                32,
                0.3835263441079304
            ],
            [
                33,
                0.4538006808288595
            ],
            [
                34,
                0.377854595732063
            ],
            [
                35,
                0.4441182286409853
            ],
            [
                36,
                0.3711051241240742
            ],
            [
                37,
                0.4368832458780222
            ],
            [
                38,
                0.3650125745817283
            ],
            [
                39,
                0.4299531757156812
            ],
            [
                40,
                0.3597326737841716
            ],
            [
                41,
                0.42351904022508174
            ],
            [
                42,
                0.3551311025374192
            ],
            [
                43,
                0.41476746645067564
            ],
            [
                44,
                0.3502290431000637
            ],
            [
                45,
                0.41002087507760565
            ],
            [
                46,
                0.3441738691124218
            ],
            [
                47,
                0.40372017628762324
            ],
            [
                48,
                0.3402052194984331
            ],
            [
                49,
                0.39858462759277924
            ],
            [
                50,
                0.336404094093582
            ]
        ],
        "accuracy_fit": [
            [
                1,
                0.528061950897663
            ],
            [
                2,
                0.6760218078272042
            ],
            [
                3,
                0.673827134770983
            ],
            [
                4,
                0.7781921727957773
            ],
            [
                5,
                0.7062193978539432
            ],
            [
                6,
                0.8059103378824183
            ],
            [
                7,
                0.7291523422578742
            ],
            [
                8,
                0.8201826579157551
            ],
            [
                9,
                0.749716984408098
            ],
            [
                10,
                0.8278501232767304
            ],
            [
                11,
                0.764503246865993
            ],
            [
                12,
                0.833593777129562
            ],
            [
                13,
                0.7789422509289162
            ],
            [
                14,
                0.8394485536687848
            ],
            [
                15,
                0.7891030315657881
            ],
            [
                16,
                0.8438448449491267
            ],
            [
                17,
                0.7968816196131542
            ],
            [
                18,
                0.8479286036739939
            ],
            [
                19,
                0.8047643851790116
            ],
            [
                20,
                0.8510192033892419
            ],
            [
                21,
                0.8117095530784457
            ],
            [
                22,
                0.8548598812376289
            ],
            [
                23,
                0.8179115880126402
            ],
            [
                24,
                0.8566725700593811
            ],
            [
                25,
                0.8231621349446124
            ],
            [
                26,
                0.8588950237871998
            ],
            [
                27,
                0.8269472514498039
            ],
            [
                28,
                0.8617355974580686
            ],
            [
                29,
                0.8324408792582563
            ],
            [
                30,
                0.8635205056082231
            ],
            [
                31,
                0.8348716880230579
            ],
            [
                32,
                0.8651387297287914
            ],
            [
                33,
                0.8392332534639023
            ],
            [
                34,
                0.8679723582317604
            ],
            [
                35,
                0.8417335139076987
            ],
            [
                36,
                0.8700072924262944
            ],
            [
                37,
                0.8454908497412925
            ],
            [
                38,
                0.8721811299788171
            ],
            [
                39,
                0.8473382644025419
            ],
            [
                40,
                0.8735146022155086
            ],
            [
                41,
                0.8505608223078792
            ],
            [
                42,
                0.874931416466993
            ],
            [
                43,
                0.8528874535541896
            ],
            [
                44,
                0.8764593534048685
            ],
            [
                45,
                0.8545751293537521
            ],
            [
                46,
                0.8791332430461506
            ],
            [
                47,
                0.8563044761607113
            ],
            [
                48,
                0.8807445219988194
            ],
            [
                49,
                0.8587769559329097
            ],
            [
                50,
                0.8803278119248533
            ]
        ],
        "loss_eval": [
            [
                1,
                1.3314490978641342
            ],
            [
                2,
                0.777335650575305
            ],
            [
                3,
                1.1503585794278852
            ],
            [
                4,
                0.6037187440898805
            ],
            [
                5,
                1.1378997261650312
            ],
            [
                6,
                0.5393968215861553
            ],
            [
                7,
                1.1225912414903891
            ],
            [
                8,
                0.5058422822174754
            ],
            [
                9,
                1.101210300150835
            ],
            [
                10,
                0.47843987038114677
            ],
            [
                11,
                1.0918886592764498
            ],
            [
                12,
                0.46091736230885966
            ],
            [
                13,
                1.0884376048495599
            ],
            [
                14,
                0.4463943287388874
            ],
            [
                15,
                1.0678801781979266
            ],
            [
                16,
                0.4339048403171339
            ],
            [
                17,
                1.065184383072589
            ],
            [
                18,
                0.4261521292795295
            ],
            [
                19,
                1.0606758591881498
            ],
            [
                20,
                0.4147168745874415
            ],
            [
                21,
                1.0507483086403286
            ],
            [
                22,
                0.40915332281405803
            ],
            [
                23,
                1.0512355649585479
            ],
            [
                24,
                0.3990093217795712
            ],
            [
                25,
                1.0690225540176623
            ],
            [
                26,
                0.3951900140015794
            ],
            [
                27,
                1.0403160214672382
            ],
            [
                28,
                0.3885302501512239
            ],
            [
                29,
                1.0337587459044673
            ],
            [
                30,
                0.38665169544738315
            ],
            [
                31,
                1.0278827787388964
            ],
            [
                32,
                0.3848597520815735
            ],
            [
                33,
                1.0474001958736625
            ],
            [
                34,
                0.37404993757860006
            ],
            [
                35,
                1.043815008474856
            ],
            [
                36,
                0.37135136695714455
            ],
            [
                37,
                1.041834045479269
            ],
            [
                38,
                0.36710480000763224
            ],
            [
                39,
                1.0355759888279195
            ],
            [
                40,
                0.3626709387506956
            ],
            [
                41,
                1.0488142019408486
            ],
            [
                42,
                0.3603846529085206
            ],
            [
                43,
                1.0395659242258226
            ],
            [
                44,
                0.35813599649889677
            ],
            [
                45,
                1.0378204792452475
            ],
            [
                46,
                0.3529277773039483
            ],
            [
                47,
                1.0334224043365123
            ],
            [
                48,
                0.35063055846056607
            ],
            [
                49,
                1.036131417508028
            ],
            [
                50,
                0.34757757644164766
            ]
        ],
        "accuracy_eval": [
            [
                1,
                0.40099958350687215
            ],
            [
                2,
                0.7427738442315702
            ],
            [
                3,
                0.43590170762182423
            ],
            [
                4,
                0.7965847563515202
            ],
            [
                5,
                0.446314035818409
            ],
            [
                6,
                0.814993752603082
            ],
            [
                7,
                0.4448146605581008
            ],
            [
                8,
                0.8239900041649313
            ],
            [
                9,
                0.4473969179508538
            ],
            [
                10,
                0.8342357351103706
            ],
            [
                11,
                0.4534777176176593
            ],
            [
                12,
                0.8400666389004582
            ],
            [
                13,
                0.4508121615993336
            ],
            [
                14,
                0.8443981674302374
            ],
            [
                15,
                0.4567263640149938
            ],
            [
                16,
                0.8469804248229904
            ],
            [
                17,
                0.45855893377759266
            ],
            [
                18,
                0.8507288629737609
            ],
            [
                19,
                0.4515618492294877
            ],
            [
                20,
                0.854310703873386
            ],
            [
                21,
                0.45722615576842984
            ],
            [
                22,
                0.8563931695127031
            ],
            [
                23,
                0.4545605997501041
            ],
            [
                24,
                0.8596418159100375
            ],
            [
                25,
                0.46030820491461893
            ],
            [
                26,
                0.8608912952936276
            ],
            [
                27,
                0.45822573927530197
            ],
            [
                28,
                0.8630570595585173
            ],
            [
                29,
                0.46547271970012494
            ],
            [
                30,
                0.8638067471886713
            ],
            [
                31,
                0.46355685131195334
            ],
            [
                32,
                0.8622240733027905
            ],
            [
                33,
                0.4640566430653894
            ],
            [
                34,
                0.8663890045814244
            ],
            [
                35,
                0.46314035818408994
            ],
            [
                36,
                0.8677217825905873
            ],
            [
                37,
                0.4626405664306539
            ],
            [
                38,
                0.8687213660974594
            ],
            [
                39,
                0.46122448979591835
            ],
            [
                40,
                0.8713036234902124
            ],
            [
                41,
                0.4630570595585173
            ],
            [
                42,
                0.870637234485631
            ],
            [
                43,
                0.4640566430653894
            ],
            [
                44,
                0.8731361932528113
            ],
            [
                45,
                0.4617242815493544
            ],
            [
                46,
                0.8745522698875469
            ],
            [
                47,
                0.4663890045814244
            ],
            [
                48,
                0.8756351520199916
            ],
            [
                49,
                0.46738858808829653
            ],
            [
                50,
                0.8758850478967097
            ]
        ]
    }
]